rolilib/__init__.py
rolilib/exceptions.py
rolilib/item.py
rolilib/player.py
rolilib/utils.py
rolilib-0.1.2.dist-info/METADATA
rolilib-0.1.2.dist-info/WHEEL
rolilib-0.1.2.dist-info/top_level.txt
rolilib-0.1.2.dist-info/RECORD
