Metadata-Version: 2.1
Name: rolilib
Version: 0.1.2
Summary: API Wrapper for Rolimon's
Author: ThunderFound
Author-email: <contact.thunderfound@gmail.com>
Keywords: python,api,rolimons
Classifier: Programming Language :: Python :: 3
Requires-Dist: requests
Requires-Dist: datetime
